FSM Practice/fsm.v
module fsm_fixed #(
    parameter s0 = 2'b00, 
    parameter s5 = 2'b01, 
    parameter s10 = 2'b10, 
    parameter s15 = 2'b11
) (
    input wire clk, // Added clock input
    input wire reset, 
    input wire [1:0] coins, // 2-bit input: 00=no coin, 01=5 cents, 10=10 cents
    output reg open // State is 2-bit, so curr/nxt should be 2-bit
);

    reg [1:0] nxt, curr;

    // --- State Register: Synchronous update on posedge clk, asynchronous reset ---
    always @(posedge clk or posedge reset) begin
        if (reset) 
            curr <= s0;
        else 
            curr <= nxt;
    end

    // --- Next State Logic: Combinationally determines nxt based on curr and coins ---
    always @(*) begin
        nxt = curr; // Default: stay in current state
        case (curr)
            s0: begin
                if (coins == 2'b10)      // 10 cents -> s10
                    nxt = s10;
                else if (coins == 2'b01) // 5 cents -> s5
                    nxt = s5;
                // else (coins == 2'b00) nxt = s0 (default)
            end
            s5: begin
                if (coins == 2'b10)      // 10 cents -> s15 (5+10)
                    nxt = s15;
                else if (coins == 2'b01) // 5 cents -> s10 (5+5)
                    nxt = s10;
                // else nxt = s5
            end
            s10: begin
                if (coins != 2'b00)      // Any coin (5 or 10) -> s15
                    nxt = s15;
                // else nxt = s10
            end
            s15: begin
                // Once open, we assume the machine resets to s0 (next clock cycle)
                if (coins == 2'b10)      // 10 cents -> s10
                    nxt = s10;
                else if (coins == 2'b01) // 5 cents -> s5
                    nxt = s5; 
                else nxt = s0;
            end
            default: nxt = s0;
        endcase
    end

    // --- Output Logic: Moore Machine (Output depends only on state) ---
    always @(curr) begin
        if (curr == s15)
            open = 1'b1;
        else
            open = 1'b0;
    end
    
endmodule

FSM Practice/tb_fsm.v
`timescale 1ns / 1ps

module tb_fsm;

    // --- Signals for DUT (Device Under Test) ---
    reg clk;
    reg reset;
    reg [1:0] coins;
    wire open;
    
    // --- Instantiate the FSM (Device Under Test) ---
    fsm_fixed DUT (
        .clk(clk),
        .reset(reset),
        .coins(coins),
        .open(open)
    );

    // --- Clock Generation ---
    parameter CLK_PERIOD = 10; // 10 ns period (100 MHz)
    initial begin
        clk = 0;
        forever #(CLK_PERIOD/2) clk = ~clk; // Toggle every 5 ns
    end

    // --- Test Stimulus ---
    initial begin
        // Initialize inputs
        reset = 1;
        coins = 2'b00;
        
        // Wait for a short time and then de-assert reset
        @(posedge clk);
        #1; // Wait 1 ns after clock edge
        reset = 0;
        $display("\n--- Simulation Started ---");
        
        // --- Test Sequence 1: 5 cents (s0->s5), 5 cents (s5->s10), 5 cents (s10->s15) ---
        $display("Time=%0t: Starting Sequence 1 (5, 5, 5)", $time);
        
        @(posedge clk); coins = 2'b01; // Insert 5 cents (s0 -> s5)
        @(posedge clk); coins = 2'b01; // Insert 5 cents (s5 -> s10)
        @(posedge clk); coins = 2'b01; // Insert 5 cents (s10 -> s15) -> OPEN=1

        // --- Test Sequence 2: 10 cents (s0->s10), 10 cents (s0->s15) ---
        $display("Time=%0t: Starting Sequence 2 (10, 10)", $time);

        @(posedge clk); coins = 2'b10; // Insert 10 cents (s0 -> s10)
        @(posedge clk); coins = 2'b10; // Insert 10 cents (s10 -> s15) -> OPEN=1

        // --- Test Sequence 3: 5 cents (s0->s5), 10 cents (s5->s15) ---
        $display("Time=%0t: Starting Sequence 3 (5, 10)", $time);

        @(posedge clk); coins = 2'b01; // Insert 5 cents (s0 -> s5)
        @(posedge clk); coins = 2'b10; // Insert 10 cents (s5 -> s15) -> OPEN=1
        @(posedge clk); coins = 2'b00; // After s15, it should transition to s0
        $display("Time=%0t: --- Simulation Finished ---", $time);
        $finish;
    end

    // --- Monitor and Display Changes ---
    initial begin
        $monitor("Time=%0t | clk=%b reset=%b | coins=%b | curr_state=%d | open=%b", 
                 $time, clk, reset, coins, DUT.curr, open);
    end
    initial begin
    // Specify the VCD file name
    $dumpfile("fsm.vcd"); 
    
    // Dump all signals in the testbench module (or specific modules/signals)
    $dumpvars(0, tb_fsm); 
    
    // ... rest of your stimulus code
end

endmodule

FSM Practice/fsm.vcd
$date
	Tue Nov 11 22:07:37 2025
$end
$version
	Icarus Verilog
$end
$timescale
	1ps
$end
$scope module tb_fsm $end
$var wire 1 ! open $end
$var parameter 32 " CLK_PERIOD $end
$var reg 1 # clk $end
$var reg 2 $ coins [1:0] $end
$var reg 1 % reset $end
$scope module DUT $end
$var wire 1 # clk $end
$var wire 2 & coins [1:0] $end
$var wire 1 % reset $end
$var parameter 2 ' s0 $end
$var parameter 2 ( s10 $end
$var parameter 2 ) s15 $end
$var parameter 2 * s5 $end
$var reg 2 + curr [1:0] $end
$var reg 2 , nxt [1:0] $end
$var reg 1 ! open $end
$upscope $end
$upscope $end
$enddefinitions $end
$comment Show the parameter values. $end
$dumpall
b1 *
b11 )
b10 (
b0 '
b1010 "
$end
#0
$dumpvars
b0 ,
b0 +
b0 &
1%
b0 $
0#
0!
$end
#5000
1#
#6000
0%
#10000
0#
#15000
b1 ,
b1 $
b1 &
1#
#20000
0#
#25000
b10 ,
b1 +
1#
#30000
0#
#35000
b11 ,
b10 +
1#
#40000
0#
#45000
1!
b11 +
b10 ,
b10 $
b10 &
1#
#50000
0#
#55000
0!
b11 ,
b10 +
1#
#60000
0#
#65000
1!
b11 +
b1 ,
b1 $
b1 &
1#
#70000
0#
#75000
0!
b1 +
b11 ,
b10 $
b10 &
1#
#80000
0#
#85000
1!
b11 +
b0 ,
b0 $
b0 &
1#
#90000
0#
#95000
0!
b0 +
1#
